regression_model/VERSION
regression_model/__init__.py
regression_model/pipeline.py
regression_model/predict.py
regression_model/train.py
regression_model/config/__init__.py
regression_model/config/core.py
regression_model/processing/__init__.py
regression_model/processing/data_manager.py
regression_model/processing/feaures.py
regression_model/processing/validation.py
no_regression_model-0.0.1.dist-info/METADATA
no_regression_model-0.0.1.dist-info/WHEEL
no_regression_model-0.0.1.dist-info/top_level.txt
no_regression_model-0.0.1.dist-info/RECORD
