Metadata-Version: 2.1
Name: no-regression-model
Version: 0.0.1
Summary: End-to-End house price prediction regression models
Home-page: https://github.com/Khannooman/HousePrice.git
Author: Nooman
Author-email: khannooman8586@gmail.com
License: BSD-3
Classifier: License :: OSI Approved :: MIT License
Classifier: Programming Language :: Python
Classifier: Programming Language :: Python :: 3
Classifier: Programming Language :: Python :: 3.6
Classifier: Programming Language :: Python :: 3.7
Classifier: Programming Language :: Python :: 3.8
Classifier: Programming Language :: Python :: 3.9
Classifier: Programming Language :: Python :: Implementation :: CPython
Classifier: Programming Language :: Python :: Implementation :: PyPy
Requires-Python: >=3.6.0
Requires-Dist: feature-engine==1.8.1
Requires-Dist: numpy==2.1.1
Requires-Dist: pandas==2.2.2
Requires-Dist: pydantic==2.9.1
Requires-Dist: scikit-learn==1.5.1
